.DS_Store
mlipdockers/__init__.py
mlipdockers/core.py
mlipdockers/dkreq.py
mlipdockers-0.0.8.dist-info/METADATA
mlipdockers-0.0.8.dist-info/WHEEL
mlipdockers-0.0.8.dist-info/top_level.txt
mlipdockers-0.0.8.dist-info/RECORD
